{
"meta":{"test_sets":[],"test_metrics":[],"learn_metrics":[{"best_value":"Min","name":"Logloss"}],"launch_mode":"Train","parameters":"","iteration_count":290,"learn_sets":["learn"],"name":"experiment"},
"iterations":[
{"learn":[0.6895031375],"iteration":0,"passed_time":0.0006620009963,"remaining_time":0.1913182879},
{"learn":[0.6863147113],"iteration":1,"passed_time":0.001120198873,"remaining_time":0.1613086377},
{"learn":[0.6829283315],"iteration":2,"passed_time":0.001657836823,"remaining_time":0.1585997228},
{"learn":[0.6793811015],"iteration":3,"passed_time":0.002171763065,"remaining_time":0.1552810592},
{"learn":[0.6763887146],"iteration":4,"passed_time":0.002507198843,"remaining_time":0.142910334},
{"learn":[0.6730160498],"iteration":5,"passed_time":0.002989958842,"remaining_time":0.1415247185},
{"learn":[0.6697925174],"iteration":6,"passed_time":0.003483229729,"remaining_time":0.1408220019},
{"learn":[0.6660129045],"iteration":7,"passed_time":0.004049548316,"remaining_time":0.1427465781},
{"learn":[0.66245903],"iteration":8,"passed_time":0.004813377531,"remaining_time":0.1502843429},
{"learn":[0.6594154906],"iteration":9,"passed_time":0.00544605637,"remaining_time":0.1524895784},
{"learn":[0.6558567416],"iteration":10,"passed_time":0.006000262553,"remaining_time":0.1521884775},
{"learn":[0.6524632941],"iteration":11,"passed_time":0.006582383429,"remaining_time":0.1524918828},
{"learn":[0.6488418202],"iteration":12,"passed_time":0.007173378288,"remaining_time":0.1528481374},
{"learn":[0.6457654278],"iteration":13,"passed_time":0.007729552408,"remaining_time":0.1523826046},
{"learn":[0.6424819685],"iteration":14,"passed_time":0.008220398188,"remaining_time":0.1507073001},
{"learn":[0.6396917459],"iteration":15,"passed_time":0.008693643254,"remaining_time":0.1488786407},
{"learn":[0.6356778745],"iteration":16,"passed_time":0.009214652474,"remaining_time":0.147976478},
{"learn":[0.6327423666],"iteration":17,"passed_time":0.009819611244,"remaining_time":0.1483852366},
{"learn":[0.6294008046],"iteration":18,"passed_time":0.01041688889,"remaining_time":0.1485777311},
{"learn":[0.6262080049],"iteration":19,"passed_time":0.0112674335,"remaining_time":0.1521103523},
{"learn":[0.6231760046],"iteration":20,"passed_time":0.01196806612,"remaining_time":0.1533052279},
{"learn":[0.6200495172],"iteration":21,"passed_time":0.01243914577,"remaining_time":0.1515314121},
{"learn":[0.6173777514],"iteration":22,"passed_time":0.0129676061,"remaining_time":0.1505369925},
{"learn":[0.6146208086],"iteration":23,"passed_time":0.0136017158,"remaining_time":0.1507523501},
{"learn":[0.6119206998],"iteration":24,"passed_time":0.01414818036,"remaining_time":0.1499707118},
{"learn":[0.608810807],"iteration":25,"passed_time":0.01480519417,"remaining_time":0.1503296638},
{"learn":[0.6060753868],"iteration":26,"passed_time":0.01537450176,"remaining_time":0.1497590357},
{"learn":[0.6037566347],"iteration":27,"passed_time":0.01580921851,"remaining_time":0.1479291161},
{"learn":[0.6009354257],"iteration":28,"passed_time":0.0164319612,"remaining_time":0.1478876508},
{"learn":[0.5982488558],"iteration":29,"passed_time":0.01695387848,"remaining_time":0.1469336135},
{"learn":[0.5956287544],"iteration":30,"passed_time":0.01754239344,"remaining_time":0.1465638678},
{"learn":[0.593236896],"iteration":31,"passed_time":0.01784136302,"remaining_time":0.1438459893},
{"learn":[0.5894803821],"iteration":32,"passed_time":0.01832133777,"remaining_time":0.1426843578},
{"learn":[0.5870162459],"iteration":33,"passed_time":0.01885385383,"remaining_time":0.1419584288},
{"learn":[0.5842626206],"iteration":34,"passed_time":0.01936455249,"remaining_time":0.1410845967},
{"learn":[0.5818490889],"iteration":35,"passed_time":0.01991284402,"remaining_time":0.1404961772},
{"learn":[0.5786598431],"iteration":36,"passed_time":0.0204451255,"remaining_time":0.1398004528},
{"learn":[0.576097437],"iteration":37,"passed_time":0.02093353704,"remaining_time":0.1388224036},
{"learn":[0.5729588264],"iteration":38,"passed_time":0.02150005539,"remaining_time":0.1383721514},
{"learn":[0.5704077888],"iteration":39,"passed_time":0.02202887244,"remaining_time":0.1376804528},
{"learn":[0.5673425031],"iteration":40,"passed_time":0.02260083116,"remaining_time":0.1372587063},
{"learn":[0.5648608538],"iteration":41,"passed_time":0.02312719399,"remaining_time":0.136560574},
{"learn":[0.5626110432],"iteration":42,"passed_time":0.02366543807,"remaining_time":0.1359386792},
{"learn":[0.5606263435],"iteration":43,"passed_time":0.02396730761,"remaining_time":0.133999038},
{"learn":[0.5583485983],"iteration":44,"passed_time":0.02444448342,"remaining_time":0.1330866319},
{"learn":[0.5558821664],"iteration":45,"passed_time":0.02498754918,"remaining_time":0.1325426522},
{"learn":[0.5535699553],"iteration":46,"passed_time":0.02559573039,"remaining_time":0.132335372},
{"learn":[0.5511166676],"iteration":47,"passed_time":0.02641605848,"remaining_time":0.1331809615},
{"learn":[0.5490051775],"iteration":48,"passed_time":0.02696535737,"remaining_time":0.1326255332},
{"learn":[0.5463626938],"iteration":49,"passed_time":0.02752619279,"remaining_time":0.1321257254},
{"learn":[0.5444354783],"iteration":50,"passed_time":0.02801857673,"remaining_time":0.1313027419},
{"learn":[0.5424582347],"iteration":51,"passed_time":0.02856999938,"remaining_time":0.1307626895},
{"learn":[0.5403303784],"iteration":52,"passed_time":0.02918161478,"remaining_time":0.1304913717},
{"learn":[0.5376265816],"iteration":53,"passed_time":0.02967958463,"remaining_time":0.1297107773},
{"learn":[0.5358459937],"iteration":54,"passed_time":0.03019195616,"remaining_time":0.1290019945},
{"learn":[0.5336272229],"iteration":55,"passed_time":0.03068094358,"remaining_time":0.1282025143},
{"learn":[0.5318604226],"iteration":56,"passed_time":0.03118565282,"remaining_time":0.1274781949},
{"learn":[0.5301216648],"iteration":57,"passed_time":0.03169358793,"remaining_time":0.1267743517},
{"learn":[0.5279122133],"iteration":58,"passed_time":0.03214866724,"remaining_time":0.1258702056},
{"learn":[0.525980759],"iteration":59,"passed_time":0.03265822726,"remaining_time":0.1251898712},
{"learn":[0.524319991],"iteration":60,"passed_time":0.03316360599,"remaining_time":0.1244994389},
{"learn":[0.5222257509],"iteration":61,"passed_time":0.0337321756,"remaining_time":0.1240473554},
{"learn":[0.5200497746],"iteration":62,"passed_time":0.03430310982,"remaining_time":0.1236000941},
{"learn":[0.5179663361],"iteration":63,"passed_time":0.03482663832,"remaining_time":0.1229815666},
{"learn":[0.5163850164],"iteration":64,"passed_time":0.03545904777,"remaining_time":0.1227428577},
{"learn":[0.5144515865],"iteration":65,"passed_time":0.03609562424,"remaining_time":0.1225063611},
{"learn":[0.5123251908],"iteration":66,"passed_time":0.0366380034,"remaining_time":0.1219443994},
{"learn":[0.5106153963],"iteration":67,"passed_time":0.03716877354,"remaining_time":0.1213451136},
{"learn":[0.5087152423],"iteration":68,"passed_time":0.03765737457,"remaining_time":0.1206127504},
{"learn":[0.5068011012],"iteration":69,"passed_time":0.03814039483,"remaining_time":0.1198698123},
{"learn":[0.5047169308],"iteration":70,"passed_time":0.0386681109,"remaining_time":0.1192720604},
{"learn":[0.5026935766],"iteration":71,"passed_time":0.0392282774,"remaining_time":0.1187745066},
{"learn":[0.5009863277],"iteration":72,"passed_time":0.039748491,"remaining_time":0.1181564732},
{"learn":[0.499209035],"iteration":73,"passed_time":0.04029352755,"remaining_time":0.1176135399},
{"learn":[0.4971673466],"iteration":74,"passed_time":0.04085009663,"remaining_time":0.1171036103},
{"learn":[0.4956810736],"iteration":75,"passed_time":0.04139897717,"remaining_time":0.1165708041},
{"learn":[0.4940102213],"iteration":76,"passed_time":0.04196618726,"remaining_time":0.1160882842},
{"learn":[0.4921291685],"iteration":77,"passed_time":0.042510588,"remaining_time":0.1155415982},
{"learn":[0.4903743738],"iteration":78,"passed_time":0.04307929631,"remaining_time":0.1150598927},
{"learn":[0.4885154944],"iteration":79,"passed_time":0.04366134127,"remaining_time":0.1146110208},
{"learn":[0.4866947649],"iteration":80,"passed_time":0.04419923492,"remaining_time":0.1140449395},
{"learn":[0.4850054619],"iteration":81,"passed_time":0.04469898436,"remaining_time":0.1133827896},
{"learn":[0.4833968114],"iteration":82,"passed_time":0.04526085797,"remaining_time":0.1128794891},
{"learn":[0.4818256281],"iteration":83,"passed_time":0.0458003166,"remaining_time":0.1123198241},
{"learn":[0.480124209],"iteration":84,"passed_time":0.04633059648,"remaining_time":0.1117384974},
{"learn":[0.4786926784],"iteration":85,"passed_time":0.04701716473,"remaining_time":0.1115290884},
{"learn":[0.4767962201],"iteration":86,"passed_time":0.04755266751,"remaining_time":0.1109562242},
{"learn":[0.4750354137],"iteration":87,"passed_time":0.04805814156,"remaining_time":0.1103152795},
{"learn":[0.4731794028],"iteration":88,"passed_time":0.04857910911,"remaining_time":0.10971237},
{"learn":[0.471689932],"iteration":89,"passed_time":0.04911406683,"remaining_time":0.1091423707},
{"learn":[0.4699199491],"iteration":90,"passed_time":0.04963174231,"remaining_time":0.1085353486},
{"learn":[0.4680900847],"iteration":91,"passed_time":0.05012328669,"remaining_time":0.10787403},
{"learn":[0.4662759888],"iteration":92,"passed_time":0.05068919205,"remaining_time":0.1073738799},
{"learn":[0.4645669007],"iteration":93,"passed_time":0.05121855245,"remaining_time":0.1067961306},
{"learn":[0.46297185],"iteration":94,"passed_time":0.05170953521,"remaining_time":0.1061406249},
{"learn":[0.4613047048],"iteration":95,"passed_time":0.05217816693,"remaining_time":0.105443379},
{"learn":[0.4602481036],"iteration":96,"passed_time":0.05238549841,"remaining_time":0.1042309401},
{"learn":[0.4588539506],"iteration":97,"passed_time":0.0528613575,"remaining_time":0.1035651086},
{"learn":[0.4566184308],"iteration":98,"passed_time":0.05335893239,"remaining_time":0.102945011},
{"learn":[0.4550117054],"iteration":99,"passed_time":0.05379345395,"remaining_time":0.1022075625},
{"learn":[0.453588249],"iteration":100,"passed_time":0.05442013651,"remaining_time":0.101835701},
{"learn":[0.4523114493],"iteration":101,"passed_time":0.05499737635,"remaining_time":0.1013677133},
{"learn":[0.4509067497],"iteration":102,"passed_time":0.05553821391,"remaining_time":0.1008315146},
{"learn":[0.4491187094],"iteration":103,"passed_time":0.05634869889,"remaining_time":0.1007774807},
{"learn":[0.4476146229],"iteration":104,"passed_time":0.05693100069,"remaining_time":0.1003070012},
{"learn":[0.4463022702],"iteration":105,"passed_time":0.05752148702,"remaining_time":0.09984861897},
{"learn":[0.4449899578],"iteration":106,"passed_time":0.05803497093,"remaining_time":0.09925607178},
{"learn":[0.4432983858],"iteration":107,"passed_time":0.05855427989,"remaining_time":0.098674805},
{"learn":[0.441917606],"iteration":108,"passed_time":0.05904403326,"remaining_time":0.09804559652},
{"learn":[0.4402078149],"iteration":109,"passed_time":0.05955350254,"remaining_time":0.09745118597},
{"learn":[0.438949314],"iteration":110,"passed_time":0.06015052963,"remaining_time":0.09699950273},
{"learn":[0.4372410187],"iteration":111,"passed_time":0.06062540361,"remaining_time":0.09635108787},
{"learn":[0.4358857528],"iteration":112,"passed_time":0.06119013494,"remaining_time":0.09584649456},
{"learn":[0.4346975427],"iteration":113,"passed_time":0.0617529246,"remaining_time":0.09533784851},
{"learn":[0.4332348307],"iteration":114,"passed_time":0.06219142427,"remaining_time":0.09463912388},
{"learn":[0.4319419984],"iteration":115,"passed_time":0.06275557002,"remaining_time":0.09413335502},
{"learn":[0.4304625214],"iteration":116,"passed_time":0.06330956902,"remaining_time":0.09361158496},
{"learn":[0.4293261794],"iteration":117,"passed_time":0.06381247298,"remaining_time":0.09301479113},
{"learn":[0.4280018313],"iteration":118,"passed_time":0.06434632631,"remaining_time":0.09246404872},
{"learn":[0.4265073989],"iteration":119,"passed_time":0.06492475673,"remaining_time":0.0919767387},
{"learn":[0.425237984],"iteration":120,"passed_time":0.06548842419,"remaining_time":0.09146730321},
{"learn":[0.424326123],"iteration":121,"passed_time":0.06603110983,"remaining_time":0.09092808567},
{"learn":[0.4232458248],"iteration":122,"passed_time":0.06657850586,"remaining_time":0.09039520714},
{"learn":[0.4222553377],"iteration":123,"passed_time":0.06716533597,"remaining_time":0.08991488525},
{"learn":[0.4211735431],"iteration":124,"passed_time":0.06795400583,"remaining_time":0.0896992877},
{"learn":[0.4199044301],"iteration":125,"passed_time":0.06844890335,"remaining_time":0.08909222341},
{"learn":[0.4187160836],"iteration":126,"passed_time":0.06896078175,"remaining_time":0.08850871988},
{"learn":[0.417345002],"iteration":127,"passed_time":0.06945512564,"remaining_time":0.08790414339},
{"learn":[0.4160081562],"iteration":128,"passed_time":0.06996747719,"remaining_time":0.0873237506},
{"learn":[0.414786541],"iteration":129,"passed_time":0.07055171383,"remaining_time":0.08683287856},
{"learn":[0.4135476508],"iteration":130,"passed_time":0.07113471708,"remaining_time":0.08633908409},
{"learn":[0.4122739464],"iteration":131,"passed_time":0.07171396082,"remaining_time":0.08583943795},
{"learn":[0.4112690733],"iteration":132,"passed_time":0.07225496903,"remaining_time":0.08529345969},
{"learn":[0.4098725636],"iteration":133,"passed_time":0.0727235705,"remaining_time":0.08466326118},
{"learn":[0.4087990911],"iteration":134,"passed_time":0.07328231812,"remaining_time":0.08413895784},
{"learn":[0.407695117],"iteration":135,"passed_time":0.07379839322,"remaining_time":0.08356582762},
{"learn":[0.4061776342],"iteration":136,"passed_time":0.07431356655,"remaining_time":0.08299252323},
{"learn":[0.4049966941],"iteration":137,"passed_time":0.07478940452,"remaining_time":0.08237673542},
{"learn":[0.4039185325],"iteration":138,"passed_time":0.07528043408,"remaining_time":0.08177946436},
{"learn":[0.4026765972],"iteration":139,"passed_time":0.07576722527,"remaining_time":0.08117916993},
{"learn":[0.4016281813],"iteration":140,"passed_time":0.07627990843,"remaining_time":0.08060784649},
{"learn":[0.4003479555],"iteration":141,"passed_time":0.07682906406,"remaining_time":0.08007536254},
{"learn":[0.3990869653],"iteration":142,"passed_time":0.07757367506,"remaining_time":0.07974356807},
{"learn":[0.3979616948],"iteration":143,"passed_time":0.07810244417,"remaining_time":0.07918720034},
{"learn":[0.3966983578],"iteration":144,"passed_time":0.07860496859,"remaining_time":0.07860496859},
{"learn":[0.3956170137],"iteration":145,"passed_time":0.07912743721,"remaining_time":0.07804349971},
{"learn":[0.3945975617],"iteration":146,"passed_time":0.07967100237,"remaining_time":0.07750308394},
{"learn":[0.3934920561],"iteration":147,"passed_time":0.08041198342,"remaining_time":0.07715203814},
{"learn":[0.391853386],"iteration":148,"passed_time":0.08102900094,"remaining_time":0.07667845056},
{"learn":[0.3908533874],"iteration":149,"passed_time":0.08159428362,"remaining_time":0.07615466472},
{"learn":[0.3898182047],"iteration":150,"passed_time":0.08217683427,"remaining_time":0.07564622493},
{"learn":[0.3887488535],"iteration":151,"passed_time":0.08268894725,"remaining_time":0.07507286},
{"learn":[0.3875804312],"iteration":152,"passed_time":0.08327388876,"remaining_time":0.07456550824},
{"learn":[0.3863777917],"iteration":153,"passed_time":0.08376229402,"remaining_time":0.07397189602},
{"learn":[0.3852788306],"iteration":154,"passed_time":0.08434382246,"remaining_time":0.0734607486},
{"learn":[0.3840747663],"iteration":155,"passed_time":0.08485755066,"remaining_time":0.07289046018},
{"learn":[0.3831696845],"iteration":156,"passed_time":0.08534836448,"remaining_time":0.07230148073},
{"learn":[0.3820749064],"iteration":157,"passed_time":0.08593530589,"remaining_time":0.07179405302},
{"learn":[0.3810605809],"iteration":158,"passed_time":0.08645224111,"remaining_time":0.07122794708},
{"learn":[0.3800101636],"iteration":159,"passed_time":0.08709825832,"remaining_time":0.07076733488},
{"learn":[0.3789582484],"iteration":160,"passed_time":0.08761344192,"remaining_time":0.07019959011},
{"learn":[0.3781685968],"iteration":161,"passed_time":0.08815127906,"remaining_time":0.06965039333},
{"learn":[0.3768529664],"iteration":162,"passed_time":0.08869315081,"remaining_time":0.06910447947},
{"learn":[0.3759543399],"iteration":163,"passed_time":0.08927173819,"remaining_time":0.06858682325},
{"learn":[0.3750867377],"iteration":164,"passed_time":0.08979387407,"remaining_time":0.06802566217},
{"learn":[0.3741697507],"iteration":165,"passed_time":0.09024078084,"remaining_time":0.06740877605},
{"learn":[0.3731852702],"iteration":166,"passed_time":0.09080229145,"remaining_time":0.06687833442},
{"learn":[0.3723084913],"iteration":167,"passed_time":0.09133671838,"remaining_time":0.06632785501},
{"learn":[0.371395395],"iteration":168,"passed_time":0.09196432327,"remaining_time":0.06584427879},
{"learn":[0.370692647],"iteration":169,"passed_time":0.09261536021,"remaining_time":0.06537554838},
{"learn":[0.3698102641],"iteration":170,"passed_time":0.09314795789,"remaining_time":0.06482226309},
{"learn":[0.3689340738],"iteration":171,"passed_time":0.09368902945,"remaining_time":0.06427503183},
{"learn":[0.3679098808],"iteration":172,"passed_time":0.09421669359,"remaining_time":0.06371880434},
{"learn":[0.3671039881],"iteration":173,"passed_time":0.09453033366,"remaining_time":0.06302022244},
{"learn":[0.3657622039],"iteration":174,"passed_time":0.09507836264,"remaining_time":0.06248006688},
{"learn":[0.3645762492],"iteration":175,"passed_time":0.09567579782,"remaining_time":0.06197182358},
{"learn":[0.3635465951],"iteration":176,"passed_time":0.0963080035,"remaining_time":0.0614847706},
{"learn":[0.3620999438],"iteration":177,"passed_time":0.09686846565,"remaining_time":0.06095094468},
{"learn":[0.3611889024],"iteration":178,"passed_time":0.09738728891,"remaining_time":0.06039100038},
{"learn":[0.3602829429],"iteration":179,"passed_time":0.09791766809,"remaining_time":0.05983857494},
{"learn":[0.3592414642],"iteration":180,"passed_time":0.0984689412,"remaining_time":0.05929897564},
{"learn":[0.358242865],"iteration":181,"passed_time":0.09903794401,"remaining_time":0.05876976898},
{"learn":[0.3573869024],"iteration":182,"passed_time":0.09964526511,"remaining_time":0.05826253206},
{"learn":[0.3564605498],"iteration":183,"passed_time":0.1002393283,"remaining_time":0.05774656957},
{"learn":[0.35567203],"iteration":184,"passed_time":0.1008213659,"remaining_time":0.05722293738},
{"learn":[0.354880611],"iteration":185,"passed_time":0.1013874008,"remaining_time":0.05668972947},
{"learn":[0.354151943],"iteration":186,"passed_time":0.1019169564,"remaining_time":0.05613607757},
{"learn":[0.3532085662],"iteration":187,"passed_time":0.1024127888,"remaining_time":0.0555643854},
{"learn":[0.3525781991],"iteration":188,"passed_time":0.1030061026,"remaining_time":0.05504558921},
{"learn":[0.3517199264],"iteration":189,"passed_time":0.1034951477,"remaining_time":0.05447113034},
{"learn":[0.3509139801],"iteration":190,"passed_time":0.1039964998,"remaining_time":0.0539039449},
{"learn":[0.3499549861],"iteration":191,"passed_time":0.1044932151,"remaining_time":0.05333507854},
{"learn":[0.3488698351],"iteration":192,"passed_time":0.1050325967,"remaining_time":0.05278840352},
{"learn":[0.3478989337],"iteration":193,"passed_time":0.1055874164,"remaining_time":0.05224944318},
{"learn":[0.3468580699],"iteration":194,"passed_time":0.1061865901,"remaining_time":0.05173192851},
{"learn":[0.3461057478],"iteration":195,"passed_time":0.1066970548,"remaining_time":0.05117103646},
{"learn":[0.3452216444],"iteration":196,"passed_time":0.1072159282,"remaining_time":0.05061462602},
{"learn":[0.3443152188],"iteration":197,"passed_time":0.1077198013,"remaining_time":0.05005162486},
{"learn":[0.3433373551],"iteration":198,"passed_time":0.1082316603,"remaining_time":0.0494928698},
{"learn":[0.3426455356],"iteration":199,"passed_time":0.1087429891,"remaining_time":0.04893434509},
{"learn":[0.3417491562],"iteration":200,"passed_time":0.1092422277,"remaining_time":0.04837093665},
{"learn":[0.340840049],"iteration":201,"passed_time":0.1098067542,"remaining_time":0.04783660577},
{"learn":[0.339941815],"iteration":202,"passed_time":0.1103177479,"remaining_time":0.04727903481},
{"learn":[0.3393266898],"iteration":203,"passed_time":0.1108521297,"remaining_time":0.04673178018},
{"learn":[0.3385951349],"iteration":204,"passed_time":0.1114156534,"remaining_time":0.04619673432},
{"learn":[0.3376543158],"iteration":205,"passed_time":0.1119092947,"remaining_time":0.04563291627},
{"learn":[0.3368151223],"iteration":206,"passed_time":0.1124624473,"remaining_time":0.04509363827},
{"learn":[0.3360495879],"iteration":207,"passed_time":0.1130196881,"remaining_time":0.04455583858},
{"learn":[0.3351822348],"iteration":208,"passed_time":0.113514387,"remaining_time":0.0439936141},
{"learn":[0.3344354229],"iteration":209,"passed_time":0.1140438421,"remaining_time":0.0434452732},
{"learn":[0.3336452866],"iteration":210,"passed_time":0.114529461,"remaining_time":0.04288069867},
{"learn":[0.3328316129],"iteration":211,"passed_time":0.1151200786,"remaining_time":0.04235550062},
{"learn":[0.3323377575],"iteration":212,"passed_time":0.1156621302,"remaining_time":0.04181213156},
{"learn":[0.3316295521],"iteration":213,"passed_time":0.1162135585,"remaining_time":0.04127210489},
{"learn":[0.330829413],"iteration":214,"passed_time":0.1167119524,"remaining_time":0.04071347178},
{"learn":[0.3300852714],"iteration":215,"passed_time":0.117206661,"remaining_time":0.04015413387},
{"learn":[0.3294905303],"iteration":216,"passed_time":0.1177681151,"remaining_time":0.03961784518},
{"learn":[0.3285863555],"iteration":217,"passed_time":0.1183128714,"remaining_time":0.03907581075},
{"learn":[0.3278961589],"iteration":218,"passed_time":0.1188772232,"remaining_time":0.03854010434},
{"learn":[0.3271212435],"iteration":219,"passed_time":0.1193338002,"remaining_time":0.03796984551},
{"learn":[0.3262009412],"iteration":220,"passed_time":0.1198257658,"remaining_time":0.03741166443},
{"learn":[0.3254807632],"iteration":221,"passed_time":0.120396115,"remaining_time":0.03687808927},
{"learn":[0.3248959301],"iteration":222,"passed_time":0.1209290003,"remaining_time":0.03633292835},
{"learn":[0.3239403973],"iteration":223,"passed_time":0.1214205692,"remaining_time":0.03577570344},
{"learn":[0.3233780106],"iteration":224,"passed_time":0.1219699965,"remaining_time":0.03523577678},
{"learn":[0.3226371893],"iteration":225,"passed_time":0.1224389947,"remaining_time":0.03467298964},
{"learn":[0.3220528789],"iteration":226,"passed_time":0.1229937368,"remaining_time":0.03413482563},
{"learn":[0.3211594642],"iteration":227,"passed_time":0.1235293697,"remaining_time":0.03359131983},
{"learn":[0.3205356829],"iteration":228,"passed_time":0.124082088,"remaining_time":0.03305243391},
{"learn":[0.3199786911],"iteration":229,"passed_time":0.1246681904,"remaining_time":0.03252213662},
{"learn":[0.3192252593],"iteration":230,"passed_time":0.1251850405,"remaining_time":0.03197366836},
{"learn":[0.318796925],"iteration":231,"passed_time":0.1254346091,"remaining_time":0.03135865226},
{"learn":[0.3180077466],"iteration":232,"passed_time":0.1262107561,"remaining_time":0.03087559271},
{"learn":[0.3173551193],"iteration":233,"passed_time":0.1267148553,"remaining_time":0.03032492263},
{"learn":[0.316694889],"iteration":234,"passed_time":0.1272850652,"remaining_time":0.02979012164},
{"learn":[0.3157684553],"iteration":235,"passed_time":0.1278472122,"remaining_time":0.02925317567},
{"learn":[0.3151593905],"iteration":236,"passed_time":0.1283350655,"remaining_time":0.02869940284},
{"learn":[0.3144481509],"iteration":237,"passed_time":0.1288598143,"remaining_time":0.02815424514},
{"learn":[0.313768806],"iteration":238,"passed_time":0.1293708235,"remaining_time":0.02760632634},
{"learn":[0.3132854831],"iteration":239,"passed_time":0.1299452986,"remaining_time":0.02707193721},
{"learn":[0.3127399224],"iteration":240,"passed_time":0.130455947,"remaining_time":0.02652423819},
{"learn":[0.3119440448],"iteration":241,"passed_time":0.1310748389,"remaining_time":0.02599831515},
{"learn":[0.3113330591],"iteration":242,"passed_time":0.131578123,"remaining_time":0.02544926658},
{"learn":[0.3106748083],"iteration":243,"passed_time":0.1321001698,"remaining_time":0.02490413038},
{"learn":[0.3099205934],"iteration":244,"passed_time":0.1326782098,"remaining_time":0.02436946711},
{"learn":[0.3093202581],"iteration":245,"passed_time":0.13322622,"remaining_time":0.02382908},
{"learn":[0.3087923947],"iteration":246,"passed_time":0.1337761553,"remaining_time":0.0232889663},
{"learn":[0.3082453993],"iteration":247,"passed_time":0.1342690403,"remaining_time":0.02273911167},
{"learn":[0.307711404],"iteration":248,"passed_time":0.1348273217,"remaining_time":0.02220048268},
{"learn":[0.3070370796],"iteration":249,"passed_time":0.1354012163,"remaining_time":0.02166419462},
{"learn":[0.3062546961],"iteration":250,"passed_time":0.1359516191,"remaining_time":0.02112395675},
{"learn":[0.3057573167],"iteration":251,"passed_time":0.1365095602,"remaining_time":0.02058477495},
{"learn":[0.3047796309],"iteration":252,"passed_time":0.1370316282,"remaining_time":0.02004019859},
{"learn":[0.30399308],"iteration":253,"passed_time":0.1375558262,"remaining_time":0.01949610135},
{"learn":[0.3034231576],"iteration":254,"passed_time":0.1380719806,"remaining_time":0.01895105616},
{"learn":[0.3026692008],"iteration":255,"passed_time":0.1386559804,"remaining_time":0.01841524739},
{"learn":[0.3019136697],"iteration":256,"passed_time":0.139220016,"remaining_time":0.01787650011},
{"learn":[0.3012682414],"iteration":257,"passed_time":0.1397364056,"remaining_time":0.0173316472},
{"learn":[0.3006172582],"iteration":258,"passed_time":0.1402470506,"remaining_time":0.01678632652},
{"learn":[0.2998564513],"iteration":259,"passed_time":0.1408130279,"remaining_time":0.01624765706},
{"learn":[0.2990947965],"iteration":260,"passed_time":0.1413969706,"remaining_time":0.01571077451},
{"learn":[0.298439733],"iteration":261,"passed_time":0.1419612487,"remaining_time":0.01517143116},
{"learn":[0.2980217743],"iteration":262,"passed_time":0.1425224705,"remaining_time":0.01463158443},
{"learn":[0.2973444562],"iteration":263,"passed_time":0.1430862276,"remaining_time":0.01409182545},
{"learn":[0.2968427277],"iteration":264,"passed_time":0.1436333896,"remaining_time":0.01355031978},
{"learn":[0.2962063544],"iteration":265,"passed_time":0.1441626444,"remaining_time":0.01300715589},
{"learn":[0.2957149719],"iteration":266,"passed_time":0.1447344405,"remaining_time":0.01246776079},
{"learn":[0.2950084977],"iteration":267,"passed_time":0.1454537731,"remaining_time":0.0119402351},
{"learn":[0.2943976934],"iteration":268,"passed_time":0.1459861379,"remaining_time":0.01139668734},
{"learn":[0.2936656903],"iteration":269,"passed_time":0.146480024,"remaining_time":0.01085037215},
{"learn":[0.2932573889],"iteration":270,"passed_time":0.1470622431,"remaining_time":0.01031063697},
{"learn":[0.292686094],"iteration":271,"passed_time":0.1476468353,"remaining_time":0.009770746454},
{"learn":[0.2919887382],"iteration":272,"passed_time":0.148157595,"remaining_time":0.009225930827},
{"learn":[0.2915361265],"iteration":273,"passed_time":0.1486406016,"remaining_time":0.008679743159},
{"learn":[0.2909829753],"iteration":274,"passed_time":0.1491587017,"remaining_time":0.008135929185},
{"learn":[0.2904521221],"iteration":275,"passed_time":0.1497054283,"remaining_time":0.007593753607},
{"learn":[0.2897114308],"iteration":276,"passed_time":0.1501917412,"remaining_time":0.007048709874},
{"learn":[0.2892184696],"iteration":277,"passed_time":0.1506957684,"remaining_time":0.00650485331},
{"learn":[0.2884560154],"iteration":278,"passed_time":0.1511752437,"remaining_time":0.005960314268},
{"learn":[0.2880240383],"iteration":279,"passed_time":0.1516926641,"remaining_time":0.005417595145},
{"learn":[0.2873766526],"iteration":280,"passed_time":0.1522591385,"remaining_time":0.00487662721},
{"learn":[0.2868663604],"iteration":281,"passed_time":0.1528025261,"remaining_time":0.004334823436},
{"learn":[0.2864339654],"iteration":282,"passed_time":0.1533290294,"remaining_time":0.003792590832},
{"learn":[0.2860278538],"iteration":283,"passed_time":0.1538646685,"remaining_time":0.003250662012},
{"learn":[0.2856795301],"iteration":284,"passed_time":0.1541191284,"remaining_time":0.002703844357},
{"learn":[0.285072709],"iteration":285,"passed_time":0.1546846,"remaining_time":0.002163420979},
{"learn":[0.2846192131],"iteration":286,"passed_time":0.1552310246,"remaining_time":0.00162262395},
{"learn":[0.2840243818],"iteration":287,"passed_time":0.1557170224,"remaining_time":0.001081368211},
{"learn":[0.2833776262],"iteration":288,"passed_time":0.156275721,"remaining_time":0.0005407464393},
{"learn":[0.282785549],"iteration":289,"passed_time":0.156832544,"remaining_time":0}
]}